pyipip/__init__.py
pyipip/ipipdb.py
pyipip-0.1.1.dist-info/DESCRIPTION.rst
pyipip-0.1.1.dist-info/LICENSE.txt
pyipip-0.1.1.dist-info/METADATA
pyipip-0.1.1.dist-info/RECORD
pyipip-0.1.1.dist-info/WHEEL
pyipip-0.1.1.dist-info/metadata.json
pyipip-0.1.1.dist-info/top_level.txt
