Metadata-Version: 2.0
Name: pyipip
Version: 0.1.1
Summary: ipip.net IP address geolocation database Python library
Home-page: https://github.com/georgexsh/pyipip
Author: georgexsh
Author-email: georgexsh@gmail.com
License: MIT
Platform: UNKNOWN
Classifier: Development Status :: 4 - Beta
Classifier: Intended Audience :: Developers
Classifier: License :: OSI Approved :: MIT License
Classifier: Topic :: Software Development :: Libraries
Classifier: Programming Language :: Python :: 2
Classifier: Programming Language :: Python :: 3
Classifier: Programming Language :: Python :: Implementation :: PyPy
